aeromesh/__init__.py
aeromesh/driver.py
aeromesh/geometry/__init__.py
aeromesh/geometry/functions2D.py
aeromesh/geometry/functions3D.py
aeromesh/geometry/refines.py
aeromesh/structs/__init__.py
aeromesh/structs/structures.py
aeromesh/terrain/__init__.py
aeromesh/terrain/terrain.py
aeromesh-0.1.2.dist-info/METADATA
aeromesh-0.1.2.dist-info/WHEEL
aeromesh-0.1.2.dist-info/entry_points.txt
aeromesh-0.1.2.dist-info/licenses/LICENSE
aeromesh-0.1.2.dist-info/RECORD
