Metadata-Version: 2.4
Name: AeroMesh
Version: 0.1.2
Summary: A customizable mesher for wind farm simulations and analysis.
Project-URL: Homepage, https://github.com/NREL/AeroMesh
Project-URL: Issues, https://github.com/NREL/AeroMesh/issues
Author-email: Adrian Gushin <Adrian.Gushin@nrel.gov>, Jeffery Allen <Jeffery.Allen@nrel.gov>, Ethan Young <Ethan.Young@nrel.gov>
License-Expression: BSD-3-Clause
License-File: LICENSE
Classifier: Operating System :: OS Independent
Classifier: Programming Language :: Python :: 3
Requires-Python: >=3.8
Requires-Dist: gmsh>=4.13.1
Requires-Dist: h5py>=3.11.0
Requires-Dist: meshio>=5.3.4
Requires-Dist: numpy>=1.26.4
Requires-Dist: pyyaml>=6.0.1
Requires-Dist: scipy==1.7.0
